<Signature xmlns="http://www.w3.org/2000/09/xmldsig#">
	<SignedInfo>
		<CanonicalizationMethod Algorithm="http://www.w3.org/TR/2001/REC-xml-c14n-20010315"/>
		<SignatureMethod Algorithm="http://www.w3.org/2000/09/xmldsig#rsa-sha1"/>
		<Reference URI="#{{form.numero_factura}}">
		<Transforms>
		<Transform Algorithm="http://www.w3.org/TR/2001/REC-xml-c14n-20010315"/>
		</Transforms>
		<DigestMethod Algorithm="http://www.w3.org/2000/09/xmldsig#sha1"/>
		<DigestValue>{{ signature.digest }}</DigestValue>
		</Reference>
	</SignedInfo>
	<SignatureValue>{{ signature.firma }}</SignatureValue>
	<KeyInfo>
		<KeyValue>
			<RSAKeyValue>
			<Modulus>{% autoescape off %}
		{{ signature.modulo }}{% endautoescape %}
			</Modulus>
			<Exponent>{% autoescape off %}
		{{ signature.exponente }}{% endautoescape %}
			</Exponent>
			</RSAKeyValue>
		</KeyValue>
		<X509Data>
		<X509Certificate>
			{{ signature.certificado }}
		</X509Certificate>
		</X509Data>
	</KeyInfo>
</Signature>